[
  {
    "ContainingType": "SimpleStore.Controllers.AuthController",
    "Method": "Login",
    "RelativePath": "api/auth/login",
    "HttpMethod": "POST",
    "IsController": true,
    "Order": 0,
    "Parameters": [
      {
        "Name": "login",
        "Type": "SimpleStore.DTOs.LoginDTO",
        "IsRequired": true
      }
    ],
    "ReturnTypes": []
  },
  {
    "ContainingType": "SimpleStore.Controllers.AuthController",
    "Method": "Logout",
    "RelativePath": "api/auth/logout",
    "HttpMethod": "GET",
    "IsController": true,
    "Order": 0,
    "Parameters": [],
    "ReturnTypes": []
  },
  {
    "ContainingType": "SimpleStore.Controllers.AuthController",
    "Method": "Me",
    "RelativePath": "api/auth/me",
    "HttpMethod": "GET",
    "IsController": true,
    "Order": 0,
    "Parameters": [],
    "ReturnTypes": []
  },
  {
    "ContainingType": "SimpleStore.Controllers.AuthController",
    "Method": "Register",
    "RelativePath": "api/auth/register",
    "HttpMethod": "POST",
    "IsController": true,
    "Order": 0,
    "Parameters": [
      {
        "Name": "register",
        "Type": "SimpleStore.DTOs.RegisterDTO",
        "IsRequired": true
      }
    ],
    "ReturnTypes": []
  },
  {
    "ContainingType": "SimpleStore.Controllers.CartController",
    "Method": "AddToCart",
    "RelativePath": "api/cart",
    "HttpMethod": "POST",
    "IsController": true,
    "Order": 0,
    "Parameters": [
      {
        "Name": "cart",
        "Type": "SimpleStore.DTOs.CartDTO",
        "IsRequired": true
      }
    ],
    "ReturnTypes": []
  },
  {
    "ContainingType": "SimpleStore.Controllers.CartController",
    "Method": "GetCart",
    "RelativePath": "api/cart",
    "HttpMethod": "GET",
    "IsController": true,
    "Order": 0,
    "Parameters": [],
    "ReturnTypes": []
  },
  {
    "ContainingType": "SimpleStore.Controllers.CategoryController",
    "Method": "All",
    "RelativePath": "api/category",
    "HttpMethod": "GET",
    "IsController": true,
    "Order": 0,
    "Parameters": [],
    "ReturnTypes": []
  },
  {
    "ContainingType": "SimpleStore.Controllers.CategoryController",
    "Method": "Detail",
    "RelativePath": "api/category/{categoryId}",
    "HttpMethod": "GET",
    "IsController": true,
    "Order": 0,
    "Parameters": [
      {
        "Name": "categoryId",
        "Type": "System.Int32",
        "IsRequired": true
      }
    ],
    "ReturnTypes": []
  },
  {
    "ContainingType": "SimpleStore.Controllers.ProductsController",
    "Method": "All",
    "RelativePath": "api/products",
    "HttpMethod": "GET",
    "IsController": true,
    "Order": 0,
    "Parameters": [
      {
        "Name": "search",
        "Type": "System.String",
        "IsRequired": false
      },
      {
        "Name": "categoryId",
        "Type": "System.Nullable\u00601[[System.Int32, System.Private.CoreLib, Version=8.0.0.0, Culture=neutral, PublicKeyToken=7cec85d7bea7798e]]",
        "IsRequired": false
      }
    ],
    "ReturnTypes": []
  },
  {
    "ContainingType": "SimpleStore.Controllers.ProductsController",
    "Method": "Detail",
    "RelativePath": "api/products/{productId}",
    "HttpMethod": "GET",
    "IsController": true,
    "Order": 0,
    "Parameters": [
      {
        "Name": "productId",
        "Type": "System.Int32",
        "IsRequired": true
      }
    ],
    "ReturnTypes": []
  }
]